celery_exporter-1.5.1.dist-info/METADATA
celery_exporter-1.5.1.dist-info/WHEEL
celery_exporter-1.5.1.dist-info/entry_points.txt
celery_exporter/monitor.py
celery_exporter/core.py
celery_exporter/metrics.py
celery_exporter/__main__.py
celery_exporter/utils.py
celery_exporter/__init__.py
celery_exporter/celery_exporter.cpython-38-x86_64-linux-gnu.so
celery_exporter-1.5.1.dist-info/RECORD
