Metadata-Version: 2.1
Name: celery_exporter
Version: 1.5.1
Classifier: Development Status :: 4 - Beta
Classifier: Environment :: Console
Classifier: License :: OSI Approved :: MIT License
Classifier: Programming Language :: Python :: 3.6
Classifier: Programming Language :: Python :: 3 :: Only
Classifier: Operating System :: OS Independent
Requires-Dist: click>=7
Requires-Dist: celery>=4,<5
Requires-Dist: prometheus_client>=0.0.20
Summary: Prometheus metrics exporter for Celery
Home-Page: https://github.com/OvalMoney/celery-exporter
Author: Fabio Todaro <fbregist@gmail.com>, Nicola Martino <mroci@bruttocarattere.org>
Author-Email: Fabio Todaro <fbregist@gmail.com>, Nicola Martino <mroci@bruttocarattere.org>
License: MIT
